nonebot_plugin_dify/__init__.py
nonebot_plugin_dify/config.py
nonebot_plugin_dify/core/__init__.py
nonebot_plugin_dify/core/cache.py
nonebot_plugin_dify/core/dify_bot.py
nonebot_plugin_dify/core/dify_client.py
nonebot_plugin_dify/core/session.py
nonebot_plugin_dify/handlers/__init__.py
nonebot_plugin_dify/handlers/commands.py
nonebot_plugin_dify/handlers/message.py
nonebot_plugin_dify/handlers/perception.py
nonebot_plugin_dify/managers/__init__.py
nonebot_plugin_dify/managers/group_memory.py
nonebot_plugin_dify/managers/private_chat.py
nonebot_plugin_dify/managers/user_memory.py
nonebot_plugin_dify/services/__init__.py
nonebot_plugin_dify/services/data_cleanup.py
nonebot_plugin_dify/services/image_description.py
nonebot_plugin_dify/services/private_profiler.py
nonebot_plugin_dify/services/profiler.py
nonebot_plugin_dify/services/semantic_matcher.py
nonebot_plugin_dify/storage/__init__.py
nonebot_plugin_dify/storage/chat_recorder.py
nonebot_plugin_dify/storage/group_store.py
nonebot_plugin_dify/storage/private_recorder.py
nonebot_plugin_dify/storage/record_manager.py
nonebot_plugin_dify/storage/user_store.py
nonebot_plugin_dify/tools/__init__.py
nonebot_plugin_dify/tools/driver.py
nonebot_plugin_dify/tools/executor.py
nonebot_plugin_dify/tools/registry.py
nonebot_plugin_dify/utils/__init__.py
nonebot_plugin_dify/utils/helpers.py
nonebot_plugin_dify/utils/image.py
nonebot_plugin_dify/utils/image_cache.py
nonebot_plugin_dify/utils/permission.py
nonebot_plugin_dify/utils/prompt_utils.py
nonebot_plugin_dify/utils/reply_type.py
nonebot_plugin_dify/utils/streaming.py
nonebot_plugin_dify/utils/validation.py
nonebot_plugin_dify-0.1.14.dist-info/licenses/LICENSE
nonebot_plugin_dify-0.1.14.dist-info/METADATA
nonebot_plugin_dify-0.1.14.dist-info/WHEEL
nonebot_plugin_dify-0.1.14.dist-info/top_level.txt
nonebot_plugin_dify-0.1.14.dist-info/RECORD
