Metadata-Version: 2.4
Name: nonebot-plugin-dify
Version: 0.1.14
Summary: A Nonebot plugin for interacting with Dify
Author-email: gsskk <your.email@example.com>
License: Copyright (c) 2026 gsskk
Project-URL: Homepage, https://github.com/gsskk/nonebot-plugin-dify
Project-URL: Documentation, https://github.com/gsskk/nonebot-plugin-dify/blob/main/README.md
Project-URL: Issue Tracker, https://github.com/gsskk/nonebot-plugin-dify/issues
Classifier: Programming Language :: Python :: 3
Classifier: License :: OSI Approved :: MIT License
Classifier: Operating System :: OS Independent
Requires-Python: >=3.10
License-File: LICENSE
Requires-Dist: nonebot2>=2.3.0
Requires-Dist: nonebot-plugin-alconna>=0.50.2
Requires-Dist: nonebot-plugin-localstore>=0.7.0
Requires-Dist: nonebot-plugin-apscheduler>=0.5.0
Requires-Dist: httpx>=0.27.0
Requires-Dist: cachetools>=6.2.0
Requires-Dist: Pillow>=10.0.0
Requires-Dist: openai>=1.0.0
Provides-Extra: semantic
Requires-Dist: fastembed>=0.3.0; extra == "semantic"
Dynamic: license-file
